scribble_to_epub/__init__.py
scribble_to_epub/__main__.py
scribble_to_epub/scribblehub.py
scribble_to_epub/assets/scribblehub.css
scribblehub_to_epub-0.0.5.dist-info/METADATA
scribblehub_to_epub-0.0.5.dist-info/WHEEL
scribblehub_to_epub-0.0.5.dist-info/entry_points.txt
scribblehub_to_epub-0.0.5.dist-info/licenses/LICENSE
scribblehub_to_epub-0.0.5.dist-info/RECORD
