Metadata-Version: 2.4
Name: scribblehub-to-epub
Version: 0.0.5
Summary: This scrapes books from https://www.scribblehub.com/ and  creates epub from them
Project-URL: Homepage, https://github.com/hazel-noack/scribblehub-to-epub
Project-URL: Issues, https://github.com/hazel-noack/scribblehub-to-epub/issues
Author-email: Hazel Noack <Hazel.Noack@proton.me>
License-File: LICENSE
Classifier: Operating System :: OS Independent
Classifier: Programming Language :: Python :: 3
Requires-Python: >=3.8
Requires-Dist: arrow~=1.3.0
Requires-Dist: beautifulsoup4~=4.13.4
Requires-Dist: cloudscraper
Requires-Dist: easy-requests~=0.0.1
Requires-Dist: ebooklib~=0.19
Requires-Dist: ftfy~=6.3.1
